aplicacion/__init__.py
aplicacion/descuetos.py
aplicacion/exceptions.py
aplicacion/gestor_ventas.py
aplicacion/impuestos.py
aplicacion/precios.py
tests/__init__.py
tests/test_aplicacion_ventas.py
aplicacion_ventas_eric-0.1.0.dist-info/LICENCE
aplicacion_ventas_eric-0.1.0.dist-info/METADATA
aplicacion_ventas_eric-0.1.0.dist-info/WHEEL
aplicacion_ventas_eric-0.1.0.dist-info/top_level.txt
aplicacion_ventas_eric-0.1.0.dist-info/RECORD
