Metadata-Version: 2.1
Name: aplicacion_ventas_eric
Version: 0.1.0
Summary: Paquete para gestionar ventas, precios, impuestos y descuentos
Home-page: https://github.com/curso_python_camara/gestor/aplicacionventas
Author: DlsRage
Author-email: spc525nc1@gmail.com
Classifier: Programming Language :: Python :: 3
Classifier: License :: OSI Approved :: MIT License
Classifier: Operating System :: OS Independent
Requires-Python: >=3.7
License-File: LICENCE
